pdm_datareader/__init__.py
pdm_datareader/tools.py
pdm_datareader-2.5.2.dist-info/LICENSE
pdm_datareader-2.5.2.dist-info/METADATA
pdm_datareader-2.5.2.dist-info/WHEEL
pdm_datareader-2.5.2.dist-info/RECORD
