Metadata-Version: 2.3
Name: pdm-datareader
Version: 2.5.2
Summary: A small python package to execute queries to PDM without having to re-authenticate every time
License: MIT
Author: PDM TEAM
Author-email: AWL@equinor.com
Requires-Python: >=3.9.2,<4.0.0
Classifier: License :: OSI Approved :: MIT License
Classifier: Operating System :: OS Independent
Classifier: Programming Language :: Python :: 3
Classifier: Programming Language :: Python :: 3.10
Classifier: Programming Language :: Python :: 3.11
Classifier: Programming Language :: Python :: 3.12
Classifier: Programming Language :: Python :: 3.13
Requires-Dist: msal-bearer (>=1.3.0,<2.0.0)
Requires-Dist: pandas (>=2.2.2,<3.0.0)
Requires-Dist: pyodbc (>=5.1.0,<6.0.0)
Requires-Dist: sqlalchemy (>=2.0.28,<3.0.0)
Requires-Dist: urllib3 (>=2.3.0,<3.0.0)
Project-URL: Repository, https://github.com/equinor/pdm-datareader
